{"paths": {"admin/js/vendor/select2/i18n/af.js": "admin/js/vendor/select2/i18n/af.4f6fcd73488c.js", "admin/js/vendor/select2/i18n/ar.js": "admin/js/vendor/select2/i18n/ar.65aa8e36bf5d.js", "admin/js/vendor/select2/i18n/az.js": "admin/js/vendor/select2/i18n/az.270c257daf81.js", "admin/js/vendor/select2/i18n/bg.js": "admin/js/vendor/select2/i18n/bg.39b8be30d4f0.js", "admin/js/vendor/select2/i18n/bn.js": "admin/js/vendor/select2/i18n/bn.6d42b4dd5665.js", "admin/js/vendor/select2/i18n/bs.js": "admin/js/vendor/select2/i18n/bs.91624382358e.js", "admin/js/vendor/select2/i18n/ca.js": "admin/js/vendor/select2/i18n/ca.a166b745933a.js", "admin/js/vendor/select2/i18n/cs.js": "admin/js/vendor/select2/i18n/cs.4f43e8e7d33a.js", "admin/js/vendor/select2/i18n/da.js": "admin/js/vendor/select2/i18n/da.766346afe4dd.js", "admin/js/vendor/select2/i18n/de.js": "admin/js/vendor/select2/i18n/de.8a1c222b0204.js", "admin/js/vendor/select2/i18n/dsb.js": "admin/js/vendor/select2/i18n/dsb.56372c92d2f1.js", "admin/js/vendor/select2/i18n/el.js": "admin/js/vendor/select2/i18n/el.27097f071856.js", "admin/js/vendor/select2/i18n/en.js": "admin/js/vendor/select2/i18n/en.cf932ba09a98.js", "admin/js/vendor/select2/i18n/es.js": "admin/js/vendor/select2/i18n/es.66dbc2652fb1.js", "admin/js/vendor/select2/i18n/et.js": "admin/js/vendor/select2/i18n/et.2b96fd98289d.js", "admin/js/vendor/select2/i18n/eu.js": "admin/js/vendor/select2/i18n/eu.adfe5c97b72c.js", "admin/js/vendor/select2/i18n/fa.js": "admin/js/vendor/select2/i18n/fa.3b5bd1961cfd.js", "admin/js/vendor/select2/i18n/fi.js": "admin/js/vendor/select2/i18n/fi.614ec42aa9ba.js", "admin/js/vendor/select2/i18n/fr.js": "admin/js/vendor/select2/i18n/fr.05e0542fcfe6.js", "admin/js/vendor/select2/i18n/gl.js": "admin/js/vendor/select2/i18n/gl.d99b1fedaa86.js", "admin/js/vendor/select2/i18n/he.js": "admin/js/vendor/select2/i18n/he.e420ff6cd3ed.js", "admin/js/vendor/select2/i18n/hi.js": "admin/js/vendor/select2/i18n/hi.70640d41628f.js", "admin/js/vendor/select2/i18n/hr.js": "admin/js/vendor/select2/i18n/hr.a2b092cc1147.js", "admin/js/vendor/select2/i18n/hsb.js": "admin/js/vendor/select2/i18n/hsb.fa3b55265efe.js", "admin/js/vendor/select2/i18n/hu.js": "admin/js/vendor/select2/i18n/hu.6ec6039cb8a3.js", "admin/js/vendor/select2/i18n/hy.js": "admin/js/vendor/select2/i18n/hy.c7babaeef5a6.js", "admin/js/vendor/select2/i18n/id.js": "admin/js/vendor/select2/i18n/id.04debded514d.js", "admin/js/vendor/select2/i18n/is.js": "admin/js/vendor/select2/i18n/is.3ddd9a6a97e9.js", "admin/js/vendor/select2/i18n/it.js": "admin/js/vendor/select2/i18n/it.be4fe8d365b5.js", "admin/js/vendor/select2/i18n/ja.js": "admin/js/vendor/select2/i18n/ja.170ae885d74f.js", "admin/js/vendor/select2/i18n/ka.js": "admin/js/vendor/select2/i18n/ka.2083264a54f0.js", "admin/js/vendor/select2/i18n/km.js": "admin/js/vendor/select2/i18n/km.c23089cb06ca.js", "admin/js/vendor/select2/i18n/ko.js": "admin/js/vendor/select2/i18n/ko.e7be6c20e673.js", "admin/js/vendor/select2/i18n/lt.js": "admin/js/vendor/select2/i18n/lt.23c7ce903300.js", "admin/js/vendor/select2/i18n/lv.js": "admin/js/vendor/select2/i18n/lv.08e62128eac1.js", "admin/js/vendor/select2/i18n/mk.js": "admin/js/vendor/select2/i18n/mk.dabbb9087130.js", "admin/js/vendor/select2/i18n/ms.js": "admin/js/vendor/select2/i18n/ms.4ba82c9a51ce.js", "admin/js/vendor/select2/i18n/nb.js": "admin/js/vendor/select2/i18n/nb.da2fce143f27.js", "admin/js/vendor/select2/i18n/ne.js": "admin/js/vendor/select2/i18n/ne.3d79fd3f08db.js", "admin/js/vendor/select2/i18n/nl.js": "admin/js/vendor/select2/i18n/nl.997868a37ed8.js", "admin/js/vendor/select2/i18n/pl.js": "admin/js/vendor/select2/i18n/pl.6031b4f16452.js", "admin/js/vendor/select2/i18n/ps.js": "admin/js/vendor/select2/i18n/ps.38dfa47af9e0.js", "admin/js/vendor/select2/i18n/pt-BR.js": "admin/js/vendor/select2/i18n/pt-BR.e1b294433e7f.js", "admin/js/vendor/select2/i18n/pt.js": "admin/js/vendor/select2/i18n/pt.33b4a3b44d43.js", "admin/js/vendor/select2/i18n/ro.js": "admin/js/vendor/select2/i18n/ro.f75cb460ec3b.js", "admin/js/vendor/select2/i18n/ru.js": "admin/js/vendor/select2/i18n/ru.934aa95f5b5f.js", "admin/js/vendor/select2/i18n/sk.js": "admin/js/vendor/select2/i18n/sk.33d02cef8d11.js", "admin/js/vendor/select2/i18n/sl.js": "admin/js/vendor/select2/i18n/sl.131a78bc0752.js", "admin/js/vendor/select2/i18n/sq.js": "admin/js/vendor/select2/i18n/sq.5636b60d29c9.js", "admin/js/vendor/select2/i18n/sr-Cyrl.js": "admin/js/vendor/select2/i18n/sr-Cyrl.f254bb8c4c7c.js", "admin/js/vendor/select2/i18n/sr.js": "admin/js/vendor/select2/i18n/sr.5ed85a48f483.js", "admin/js/vendor/select2/i18n/sv.js": "admin/js/vendor/select2/i18n/sv.7a9c2f71e777.js", "admin/js/vendor/select2/i18n/th.js": "admin/js/vendor/select2/i18n/th.f38c20b0221b.js", "admin/js/vendor/select2/i18n/tk.js": "admin/js/vendor/select2/i18n/tk.7c572a68c78f.js", "admin/js/vendor/select2/i18n/tr.js": "admin/js/vendor/select2/i18n/tr.b5a0643d1545.js", "admin/js/vendor/select2/i18n/uk.js": "admin/js/vendor/select2/i18n/uk.8cede7f4803c.js", "admin/js/vendor/select2/i18n/vi.js": "admin/js/vendor/select2/i18n/vi.097a5b75b3e1.js", "admin/js/vendor/select2/i18n/zh-CN.js": "admin/js/vendor/select2/i18n/zh-CN.2cff662ec5f9.js", "admin/js/vendor/select2/i18n/zh-TW.js": "admin/js/vendor/select2/i18n/zh-TW.04554a227c2b.js", "admin/css/vendor/select2/LICENSE-SELECT2.md": "admin/css/vendor/select2/LICENSE-SELECT2.f94142512c91.md", "admin/css/vendor/select2/select2.css": "admin/css/vendor/select2/select2.a2194c262648.css", "admin/css/vendor/select2/select2.min.css": "admin/css/vendor/select2/select2.min.9f54e6414f87.css", "admin/js/vendor/jquery/jquery.js": "admin/js/vendor/jquery/jquery.23c7c5d2d131.js", "admin/js/vendor/jquery/jquery.min.js": "admin/js/vendor/jquery/jquery.min.dc5e7f18c8d3.js", "admin/js/vendor/jquery/LICENSE.txt": "admin/js/vendor/jquery/LICENSE.75308107741f.txt", "admin/js/vendor/select2/LICENSE.md": "admin/js/vendor/select2/LICENSE.f94142512c91.md", "admin/js/vendor/select2/select2.full.js": "admin/js/vendor/select2/select2.full.c2afdeda3058.js", "admin/js/vendor/select2/select2.full.min.js": "admin/js/vendor/select2/select2.full.min.fcd7500d8e13.js", "admin/js/vendor/xregexp/LICENSE.txt": "admin/js/vendor/xregexp/LICENSE.bf79e414957a.txt", "admin/js/vendor/xregexp/xregexp.js": "admin/js/vendor/xregexp/xregexp.efda034b9537.js", "admin/js/vendor/xregexp/xregexp.min.js": "admin/js/vendor/xregexp/xregexp.min.b0439563a5d3.js", "admin/img/gis/move_vertex_off.svg": "admin/img/gis/move_vertex_off.7a23bf31ef8a.svg", "admin/img/gis/move_vertex_on.svg": "admin/img/gis/move_vertex_on.0047eba25b67.svg", "admin/js/admin/DateTimeShortcuts.js": "admin/js/admin/DateTimeShortcuts.29d0b1965c07.js", "admin/js/admin/RelatedObjectLookups.js": "admin/js/admin/RelatedObjectLookups.d7e023e6523b.js", "admin/css/autocomplete.css": "admin/css/autocomplete.781713f30664.css", "admin/css/base.css": "admin/css/base.efb520c4bb7c.css", "admin/css/changelists.css": "admin/css/changelists.09730d6ad169.css", "admin/css/dashboard.css": "admin/css/dashboard.be83f13e4369.css", "admin/css/fonts.css": "admin/css/fonts.168bab448fee.css", "admin/css/forms.css": "admin/css/forms.6230fc2a74ac.css", "admin/css/login.css": "admin/css/login.d2a477e04949.css", "admin/css/nav_sidebar.css": "admin/css/nav_sidebar.59831780a474.css", "admin/css/responsive.css": "admin/css/responsive.5a9bb635f4d5.css", "admin/css/responsive_rtl.css": "admin/css/responsive_rtl.e13ae754cceb.css", "admin/css/rtl.css": "admin/css/rtl.775b89eb85cb.css", "admin/css/widgets.css": "admin/css/widgets.b12c020d05e0.css", "admin/fonts/LICENSE.txt": "admin/fonts/LICENSE.d273d63619c9.txt", "admin/fonts/README.txt": "admin/fonts/README.ab99e6b541ea.txt", "admin/fonts/Roboto-Bold-webfont.woff": "admin/fonts/Roboto-Bold-webfont.50d75e48e0a3.woff", "admin/fonts/Roboto-Light-webfont.woff": "admin/fonts/Roboto-Light-webfont.c73eb1ceba33.woff", "admin/fonts/Roboto-Regular-webfont.woff": "admin/fonts/Roboto-Regular-webfont.35b07eb2f871.woff", "admin/img/calendar-icons.svg": "admin/img/calendar-icons.39b290681a8b.svg", "admin/img/icon-addlink.svg": "admin/img/icon-addlink.d519b3bab011.svg", "admin/img/icon-alert.svg": "admin/img/icon-alert.034cc7d8a67f.svg", "admin/img/icon-calendar.svg": "admin/img/icon-calendar.ac7aea671bea.svg", "admin/img/icon-changelink.svg": "admin/img/icon-changelink.18d2fd706348.svg", "admin/img/icon-clock.svg": "admin/img/icon-clock.e1d4dfac3f2b.svg", "admin/img/icon-deletelink.svg": "admin/img/icon-deletelink.564ef9dc3854.svg", "admin/img/icon-no.svg": "admin/img/icon-no.439e821418cd.svg", "admin/img/icon-unknown-alt.svg": "admin/img/icon-unknown-alt.81536e128bb6.svg", "admin/img/icon-unknown.svg": "admin/img/icon-unknown.a18cb4398978.svg", "admin/img/icon-viewlink.svg": "admin/img/icon-viewlink.41eb31f7826e.svg", "admin/img/icon-yes.svg": "admin/img/icon-yes.d2f9f035226a.svg", "admin/img/inline-delete.svg": "admin/img/inline-delete.fec1b761f254.svg", "admin/img/LICENSE": "admin/img/LICENSE.2c54f4e1ca1c", "admin/img/README.txt": "admin/img/README.a70711a38d87.txt", "admin/img/search.svg": "admin/img/search.7cf54ff789c6.svg", "admin/img/selector-icons.svg": "admin/img/selector-icons.b4555096cea2.svg", "admin/img/sorting-icons.svg": "admin/img/sorting-icons.3a097b59f104.svg", "admin/img/tooltag-add.svg": "admin/img/tooltag-add.e59d620a9742.svg", "admin/img/tooltag-arrowright.svg": "admin/img/tooltag-arrowright.bbfb788a849e.svg", "admin/js/actions.js": "admin/js/actions.9fe89b71cbba.js", "admin/js/actions.min.js": "admin/js/actions.min.5f3040a29159.js", "admin/js/autocomplete.js": "admin/js/autocomplete.618a7ebf39d8.js", "admin/js/calendar.js": "admin/js/calendar.b4dcf6f850fe.js", "admin/js/cancel.js": "admin/js/cancel.50e7573ea4a7.js", "admin/js/change_form.js": "admin/js/change_form.9d8ca4f96b75.js", "admin/js/collapse.js": "admin/js/collapse.f84e7410290f.js", "admin/js/collapse.min.js": "admin/js/collapse.min.10ac29832e2c.js", "admin/js/core.js": "admin/js/core.fae39a43def0.js", "admin/js/inlines.js": "admin/js/inlines.7596b7fd289e.js", "admin/js/inlines.min.js": "admin/js/inlines.min.599e296e4c24.js", "admin/js/jquery.init.js": "admin/js/jquery.init.b7781a0897fc.js", "admin/js/nav_sidebar.js": "admin/js/nav_sidebar.7605597ddf52.js", "admin/js/popup_response.js": "admin/js/popup_response.c6cc78ea5551.js", "admin/js/prepopulate.js": "admin/js/prepopulate.bd2361dfd64d.js", "admin/js/prepopulate.min.js": "admin/js/prepopulate.min.5f7f80162256.js", "admin/js/prepopulate_init.js": "admin/js/prepopulate_init.e056047b7a7e.js", "admin/js/SelectBox.js": "admin/js/SelectBox.46d59670a7a7.js", "admin/js/SelectFilter2.js": "admin/js/SelectFilter2.d250dcb52a9a.js", "admin/js/urlify.js": "admin/js/urlify.3cabcb7a9073.js", "books_css/base.css": "books_css/base.015f83176467.css", "books_css/book.css": "books_css/book.9094fe58d707.css", "books_css/info.css": "books_css/info.05e23f7020b1.css", "books_css/searched_books_css.css": "books_css/searched_books_css.fade94d58f04.css", "books_css/vjezba.css": "books_css/vjezba.f61465ca5e47.css", "icons/352141_rate_star_icon.png": "icons/352141_rate_star_icon.51a303315d65.png", "icons/bbb.png": "icons/bbb.e9cf65077f69.png", "icons/icons8-christmas-star-48.png": "icons/icons8-christmas-star-48.7e9a83cb6048.png", "icons/icons8-christmas-star-50.png": "icons/icons8-christmas-star-50.b21a8029ab97.png", "icons/icons8-star-half-empty-48.png": "icons/icons8-star-half-empty-48.cd39895b786b.png", "icons/index.png": "icons/index.9c182864566e.png", "icons/logo-big.png": "icons/logo-big.7d318798f0f0.png", "icons/logo-small.png": "icons/logo-small.e60da794c850.png", "icons/star.png": "icons/star.9c182864566e.png", "icons/star_icon_empty.png": "icons/star_icon_empty.743d6aa52fdf.png", "icons/white-star.png": "icons/white-star.f18e99bc12df.png", "icons/xxx.png": "icons/xxx.758800555f8c.png", "logo/naslovna.jpg": "logo/naslovna.47c30eb354b0.jpg", "star/0-stars-big.png": "star/0-stars-big.d21b32f7e7c7.png", "star/0-stars-small.png": "star/0-stars-small.20a8436de048.png", "star/1-s.png": "star/1-s.74fc7a314975.png", "star/1-star-big.png": "star/1-star-big.8623b26c4bc5.png", "star/1-star-small.png": "star/1-star-small.8623b26c4bc5.png", "star/1.5-stars-big.png": "star/1.5-stars-big.8e7cb21dcd90.png", "star/1.5-stars-small.png": "star/1.5-stars-small.6ced76408a9d.png", "star/2-stars-small.png": "star/2-stars-small.273e92dbe143.png", "star/2.5-stars-big.png": "star/2.5-stars-big.5da9af8fb9c0.png", "star/2.5-stars-small.png": "star/2.5-stars-small.71ddfefbf91c.png", "star/211823_star_icon(1).png": "star/211823_star_icon(1).8cf830c6704e.png", "star/3-stars-big.png": "star/3-stars-big.65de382dd69f.png", "star/3-stars-small.png": "star/3-stars-small.ebe8a0bebf4d.png", "star/3.5-stars-big.png": "star/3.5-stars-big.b407f5cac21a.png", "star/3.5-stars-small.png": "star/3.5-stars-small.1c4789e864b3.png", "star/3.5-stars-small.svg": "star/3.5-stars-small.d642b8a3c37f.svg", "star/326487_rate_star_icon.png": "star/326487_rate_star_icon.297684959857.png", "star/4-stars-big.png": "star/4-stars-big.c5492e9a2d1f.png", "star/4-stars-small.png": "star/4-stars-small.352452bfb1b2.png", "star/4.5-stars-big.png": "star/4.5-stars-big.5cf0554fd13f.png", "star/4.5-stars-small.png": "star/4.5-stars-small.4cd44ed0248a.png", "star/5-stars-big.png": "star/5-stars-big.9fb9ce2bfdb1.png", "star/5-stars-small.png": "star/5-stars-small.c6847382b7f4.png", "star/LogoMakr-5B4g4V.png": "star/LogoMakr-5B4g4V.77e786186520.png", "star/s-0.5.png": "star/s-0.5.7ffc428fb1fd.png", "star/s-0.png": "star/s-0.69b1731068f3.png", "star/s-1.png": "star/s-1.99580924228d.png", "star/stars-0.jpg": "star/stars-0.fd2304e398ed.jpg", "star/stars-1.5.jpg": "star/stars-1.5.87211e391277.jpg", "star/stars-1.jpg": "star/stars-1.9d6204db6b94.jpg", "star/stars-2.5.jpg": "star/stars-2.5.6e7c9191012b.jpg", "star/stars-2.jpg": "star/stars-2.24f445266221.jpg", "star/stars-3.5.jpg": "star/stars-3.5.4f7dad012c5a.jpg", "star/stars-3.jpg": "star/stars-3.da3cd336c21c.jpg", "star/stars-4.5.jpg": "star/stars-4.5.80973da47a79.jpg", "star/stars-4.jpg": "star/stars-4.d8312bbbd6d2.jpg", "star/stars-5.jpg": "star/stars-5.d495037a027e.jpg", "star/star_icon.png": "star/star_icon.82299fa57c76.png", "userapp_css/changePassword.css": "userapp_css/changePassword.5217677df84e.css", "userapp_css/login_css.css": "userapp_css/login_css.d41d8cd98f00.css", "userapp_css/profile_css.css": "userapp_css/profile_css.d7e04521ce64.css", "userapp_css/register_css.css": "userapp_css/register_css.ccf64c77c95d.css"}, "version": "1.0"}